actarius/__init__.py
actarius/_version.py
actarius/cfg.py
actarius/contextmgr.py
actarius/exceptions.py
actarius/exp_obj.py
actarius/shared.py
tests/__init__.py
tests/conftest.py
tests/shared.py
tests/temp_env_var.py
tests/test_context_mgr.py
tests/test_experiment_obj.py
actarius-0.0.2.dist-info/METADATA
actarius-0.0.2.dist-info/WHEEL
actarius-0.0.2.dist-info/top_level.txt
actarius-0.0.2.dist-info/RECORD
