Metadata-Version: 2.1
Name: actarius
Version: 0.0.2
Summary: Opinionated wrappers for the mlflow tracking API.
Home-page: https://github.com/shaypal5/actarius
License: UNKNOWN
Keywords: ml,mlflow,experiments
Platform: linux
Platform: osx
Platform: windows
Classifier: Development Status :: 4 - Beta
Classifier: License :: OSI Approved :: MIT License
Classifier: Programming Language :: Python
Classifier: Programming Language :: Python :: 3
Classifier: Programming Language :: Python :: 3.5
Classifier: Programming Language :: Python :: 3.6
Classifier: Programming Language :: Python :: 3.7
Classifier: Programming Language :: Python :: 3.8
Classifier: Topic :: Software Development :: Libraries
Classifier: Topic :: Software Development :: Libraries :: Python Modules
Classifier: Topic :: Utilities
Classifier: Topic :: Other/Nonlisted Topic
Classifier: Intended Audience :: Developers
Requires-Python: >=3.6
Requires-Dist: mlflow (>=1.8.0)
Requires-Dist: gitpython
Requires-Dist: birch (>=0.0.31)
Provides-Extra: test
Requires-Dist: pandas ; extra == 'test'
Requires-Dist: databricks-cli ; extra == 'test'
Requires-Dist: pytest (>=4.6) ; extra == 'test'
Requires-Dist: coverage ; extra == 'test'
Requires-Dist: pytest-cov (==2.5.1) ; extra == 'test'
Requires-Dist: boto3 ; extra == 'test'
Requires-Dist: collective.checkdocs ; extra == 'test'
Requires-Dist: pygments ; extra == 'test'
Requires-Dist: mlflow (>=1.8.0) ; extra == 'test'
Requires-Dist: gitpython ; extra == 'test'
Requires-Dist: birch (>=0.0.31) ; extra == 'test'
